ddmtools/__init__.py
ddmtools/analysis.py
ddmtools/image/__init__.py
ddmtools/image/frame.py
ddmtools/isf.py
ddmtools/types.py
ddmtools/utils/__init__.py
ddmtools/utils/equations.py
ddmtools/utils/number.py
ddmtools/utils/progress.py
ddmtools/utils/string.py
ddmtools/utils/uncertainty.py
ddmtools-0.3.0.dist-info/LICENSE
ddmtools-0.3.0.dist-info/WHEEL
ddmtools-0.3.0.dist-info/METADATA
ddmtools-0.3.0.dist-info/RECORD
